caf/__init__.py
caf/cli.py
caf/constants.py
caf/content.py
caf/generator.py
caf/paths.py
caf/utils.py
caf/verifier.py
caf-0.2.0.dist-info/METADATA
caf-0.2.0.dist-info/WHEEL
caf-0.2.0.dist-info/entry_points.txt
caf-0.2.0.dist-info/licenses/LICENSE
caf-0.2.0.dist-info/RECORD
