Metadata-Version: 2.4
Name: caf
Version: 0.2.0
Summary: Create content addressable files
Project-URL: Homepage, https://github.com/jamesls/caf
Author-email: James Saryerwinnie <js@jamesls.com>
License: BSD
License-File: LICENSE
Keywords: caf
Classifier: Development Status :: 2 - Pre-Alpha
Classifier: Intended Audience :: Developers
Classifier: License :: OSI Approved :: Apache Software License
Classifier: Natural Language :: English
Classifier: Programming Language :: Python :: 3
Classifier: Programming Language :: Python :: 3.12
Classifier: Programming Language :: Python :: Implementation :: CPython
Requires-Python: >=3.12
Requires-Dist: click
Requires-Dist: rich>=14.1.0
